pdf_font_checker/__init__.py
pdf_font_checker/cli.py
pdf_font_checker/core.py
pdf_font_checker-0.1.1.dist-info/licenses/LICENSE
pdf_font_checker-0.1.1.dist-info/METADATA
pdf_font_checker-0.1.1.dist-info/WHEEL
pdf_font_checker-0.1.1.dist-info/entry_points.txt
pdf_font_checker-0.1.1.dist-info/top_level.txt
pdf_font_checker-0.1.1.dist-info/RECORD
