Metadata-Version: 2.4
Name: pdf-font-checker
Version: 0.1.1
Summary: Tiny helper that lists fonts used in a PDF via MuPDF (mutool).
Home-page: https://example.com/pdf-font-checker
Author: Your Name
Author-email: Your Name <you@example.com>
License: MIT
Project-URL: Homepage, https://example.com/pdf-font-checker
Classifier: Programming Language :: Python :: 3
Classifier: License :: OSI Approved :: MIT License
Classifier: Operating System :: POSIX :: Linux
Classifier: Operating System :: MacOS
Requires-Python: >=3.8
License-File: LICENSE
Dynamic: author
Dynamic: home-page
Dynamic: license-file
Dynamic: requires-python
